aco/Ant.py
aco/JobArrivalManager.py
aco/Map.py
aco/Operation.py
aco/ScheduleDecoder.py
aco/Simulator.py
aco/__init__.py
aco/misc.py
aco_djssp-0.1.1.dist-info/METADATA
aco_djssp-0.1.1.dist-info/WHEEL
aco_djssp-0.1.1.dist-info/entry_points.txt
aco_djssp-0.1.1.dist-info/licenses/LICENSE
aco_djssp-0.1.1.dist-info/RECORD
