Metadata-Version: 2.4
Name: aco-djssp
Version: 0.1.1
Summary: Ant colony scheduling optimisation package
Author-email: Ben Gorrie <bg721@ic.ac.uk>
License-File: LICENSE
Requires-Python: >=3.13
Requires-Dist: matplotlib>=3.10.3
Requires-Dist: numpy>=2.2.6
